{"numero_orden":"K5325","carrito":[{"nombre":"Aquarius Manzana 500ml","precio":1800,"cantidad":1},{"nombre":"Fanta 237ml","precio":1000,"cantidad":1},{"nombre":"Aquarius Pomelo 500ml","precio":1800,"cantidad":1},{"nombre":"Aquarius Pera 500ml","precio":1800,"cantidad":1},{"nombre":"Sprite 237ml","precio":1000,"cantidad":1},{"nombre":"Coca Cola 237ml","precio":1000,"cantidad":1},{"nombre":"Sprite 500ml","precio":2000,"cantidad":1}],"total":10400,"fecha":"2025-07-15","hora":"22:56:45","origen":"kiosco","external_reference":"qr_687706dde37ad"}